CHANGELOG.md
version_helper/__init__.py
version_helper/git_tools.py
version_helper/version.py
version_helper-0.3.1.dist-info/LICENSE.md
version_helper-0.3.1.dist-info/WHEEL
version_helper-0.3.1.dist-info/METADATA
version_helper-0.3.1.dist-info/RECORD
