Metadata-Version: 2.1
Name: version-helper
Version: 0.3.1
Summary: Package for a better version management in python projects
Home-page: https://github.com/dl6nm/version-helper
License: MIT
Keywords: git,describe,tags,version,SemVer
Author: DL6NM
Author-email: mail@dl6nm.de
Requires-Python: >=3.6,<4.0
Classifier: Development Status :: 3 - Alpha
Classifier: License :: OSI Approved :: MIT License
Classifier: Operating System :: MacOS
Classifier: Operating System :: Microsoft :: Windows
Classifier: Operating System :: POSIX :: Linux
Classifier: Programming Language :: Python :: 3
Classifier: Programming Language :: Python :: 3.6
Classifier: Programming Language :: Python :: 3.7
Classifier: Programming Language :: Python :: 3.8
Classifier: Programming Language :: Python :: 3.9
Classifier: Topic :: Software Development :: Version Control
Classifier: Topic :: Software Development :: Version Control :: Git
Project-URL: Repository, https://github.com/dl6nm/version-helper
